Paver-1.3.3.dist-info/DESCRIPTION.rst
Paver-1.3.3.dist-info/METADATA
Paver-1.3.3.dist-info/RECORD
Paver-1.3.3.dist-info/WHEEL
Paver-1.3.3.dist-info/entry_points.txt
Paver-1.3.3.dist-info/metadata.json
Paver-1.3.3.dist-info/top_level.txt
paver/__init__.py
paver/__main__.py
paver/bzr.py
paver/command.py
paver/defaults.py
paver/doctools.py
paver/easy.py
paver/git.py
paver/hg.py
paver/misctasks.py
paver/options.py
paver/path.py
paver/release.py
paver/runtime.py
paver/setuputils.py
paver/shell.py
paver/ssh.py
paver/svn.py
paver/tasks.py
paver/version.py
paver/virtual.py
paver/deps/__init__.py
paver/deps/path2.py
paver/deps/path3.py
paver/docs/articles.html
paver/docs/bzr.html
paver/docs/changelog.html
paver/docs/cmdline.html
paver/docs/credits.html
paver/docs/doctools.html
paver/docs/features.html
paver/docs/files.html
paver/docs/foreword.html
paver/docs/genindex.html
paver/docs/getting_started.html
paver/docs/hg.html
paver/docs/index.html
paver/docs/misctasks.html
paver/docs/objects.inv
paver/docs/pavement.html
paver/docs/paverfullapi.html
paver/docs/paverstdlib.html
paver/docs/py-modindex.html
paver/docs/search.html
paver/docs/searchindex.js
paver/docs/setuptools.html
paver/docs/ssh.html
paver/docs/svn.html
paver/docs/tips.html
paver/docs/virtualenv.html
paver/docs/_images/paver_banner.jpg
paver/docs/_sources/articles.rst.txt
paver/docs/_sources/bzr.rst.txt
paver/docs/_sources/changelog.rst.txt
paver/docs/_sources/cmdline.rst.txt
paver/docs/_sources/credits.rst.txt
paver/docs/_sources/doctools.rst.txt
paver/docs/_sources/features.rst.txt
paver/docs/_sources/files.rst.txt
paver/docs/_sources/foreword.rst.txt
paver/docs/_sources/getting_started.rst.txt
paver/docs/_sources/hg.rst.txt
paver/docs/_sources/index.rst.txt
paver/docs/_sources/misctasks.rst.txt
paver/docs/_sources/pavement.rst.txt
paver/docs/_sources/paverfullapi.rst.txt
paver/docs/_sources/paverstdlib.rst.txt
paver/docs/_sources/setuptools.rst.txt
paver/docs/_sources/ssh.rst.txt
paver/docs/_sources/svn.rst.txt
paver/docs/_sources/tips.rst.txt
paver/docs/_sources/virtualenv.rst.txt
paver/docs/_sources/api/modules.rst.txt
paver/docs/_sources/api/paver.deps.rst.txt
