Metadata-Version: 2.0
Name: Paver
Version: 1.3.3
Summary: Easy build, distribution and deployment scripting
Home-page: https://github.com/paver/paver
Author: Lukas Linhart
Author-email: bugs@almad.net
License: UNKNOWN
Platform: UNKNOWN
Classifier: Development Status :: 5 - Production/Stable
Classifier: Intended Audience :: Developers
Classifier: License :: OSI Approved :: BSD License
Classifier: Operating System :: OS Independent
Classifier: Programming Language :: Python
Classifier: Programming Language :: Python :: 2
Classifier: Programming Language :: Python :: 2.7
Classifier: Programming Language :: Python :: 3
Classifier: Programming Language :: Python :: 3.4
Classifier: Programming Language :: Python :: 3.5
Classifier: Programming Language :: Python :: 3.6
Classifier: Programming Language :: Python :: Implementation :: CPython
Classifier: Environment :: Console
Classifier: Topic :: Documentation
Classifier: Topic :: Utilities
Classifier: Topic :: Software Development :: Build Tools
